{
  "incidentId": "INC-1758484184712-LTY83L2BB",
  "timestamp": "2025-09-21T19:49:44.712Z",
  "status": "identified",
  "severity": "medium",
  "type": "test_incident",
  "description": "Test incident",
  "affectedSystems": [],
  "reportedBy": "system",
  "assignedTo": null,
  "timeline": [
    {
      "timestamp": "2025-09-21T19:49:44.712Z",
      "action": "Incident created",
      "actor": "system"
    },
    {
      "timestamp": "2025-09-21T19:49:44.712Z",
      "action": "Evidence added",
      "actor": "test-team",
      "details": "Test log file"
    },
    {
      "timestamp": "2025-09-21T19:49:44.712Z",
      "action": "Communication sent (internal)",
      "actor": "test-user",
      "details": "Test communication"
    }
  ],
  "evidence": [
    {
      "id": "EVID-1758484184712-R0LB8G",
      "timestamp": "2025-09-21T19:49:44.712Z",
      "type": "log_file",
      "description": "Test log file",
      "location": "/test/log.txt",
      "hash": "test123",
      "collectedBy": "test-team",
      "chainOfCustody": [
        {
          "timestamp": "2025-09-21T19:49:44.712Z",
          "actor": "test-team",
          "action": "Collected"
        }
      ]
    }
  ],
  "communications": [
    {
      "id": "COMM-1758484184712-5ESZ8Z",
      "timestamp": "2025-09-21T19:49:44.712Z",
      "type": "internal",
      "recipient": "test@medisync.example.com",
      "subject": "Test communication",
      "content": "Test content",
      "sentBy": "test-user",
      "status": "sent"
    }
  ],
  "duration": 0,
  "impact": {
    "systems": 0,
    "data": false,
    "users": "unknown",
    "financial": "unknown",
    "reputational": "unknown"
  },
  "recommendations": [
    "Review and update security policies",
    "Enhance monitoring and detection capabilities",
    "Provide additional training to relevant personnel",
    "Implement additional security controls based on root cause",
    "Conduct lessons learned session with incident response team"
  ]
}